{
	"apartments"        : { "fr" : "Appartements", "en" : "Apartments" },
	"farm"            	: { "fr" : "Ferme", "en" : "Farm" },
	"hotel"            	: { "fr" : "Hôtel", "en" : "Hotel" },
	"house"            	: { "fr" : "Maison", "en" : "House" },
	"detached"         	: { "fr" : "Détaché", "en" : "Detached" },
	"residential"      	: { "fr" : "Résidentiel", "en" : "Residential" },
	"dormitory"        	: { "fr" : "Dortoir", "en" : "Dormitory" },
	"terrace"           : { "fr" : "Terrace", "en" : "Terrace" },
	"houseboat"        	: { "fr" : "Maison bateau", "en" : "Houseboat" },
	"bungalow"         	: { "fr" : "Bungalow", "en" : "Bungalow" },
	"static_caravan"    : { "fr" : "Caravane", "en" : "Caravan" },
	"commercial"        : { "fr" : "Commercial", "en" : "Commercial" },
	"industrial"        : { "fr" : "Industriel", "en" : "Industrial" },
	"retail"            : { "fr" : "Vente au détail", "en" : "Retail" },
	"warehouse"         : { "fr" : "Entrepôt", "en" : "Warehouse" },
	"bakehouse"         : { "fr" : "Boulangerie", "en" : "Bakehouse" },
	"cathedral"         : { "fr" : "Cathédrale", "en" : "Cathedral" },
	"chapel"            : { "fr" : "Chapelle", "en" : "Chapel" },
	"church"            : { "fr" : "Église", "en" : "Church" },
	"mosque"           	: { "fr" : "Mosquée", "en" : "Mosque" },
	"temple"            : { "fr" : "Temple", "en" : "Temple" },
	"synagogue"         : { "fr" : "Synagogue", "en" : "Synagogue" },
	"shrine"            : { "fr" : "Sanctuaire", "en" : "Shrine" },
	"civic"            	: { "fr" : "Civique", "en" : "Civic" },
	"hospital"          : { "fr" : "Hôpital", "en" : "Hospital" },
	"school"            : { "fr" : "École", "en" : "School" },
	"stadium"           : { "fr" : "Stade", "en" : "Stadium" },
	"train_station"     : { "fr" : "Station de train", "en" : "Train Station" },
	"transportation"    : { "fr" : "Transport", "en" : "Transportation" },
	"university"        : { "fr" : "Université", "en" : "University" },
	"public"            : { "fr" : "Publique", "en" : "Public" },
	"barn"            	: { "fr" : "Grange", "en" : "Barn" },
	"bridge"            : { "fr" : "Pont", "en" : "Bridge" },
	"bunker"            : { "fr" : "Bunker", "en" : "Bunker" },
	"cabin"            	: { "fr" : "Cabine", "en" : "Cabin" },
	"construction"      : { "fr" : "Construction", "en" : "Construction" },
	"cowshed"           : { "fr" : "Étable", "en" : "Cowshed" },
	"digester"          : { "fr" : "Digesteur", "en" : "Digester" },
	"farm_auxiliary"    : { "fr" : "Ferme Auxiliaire", "en" : "Farm Auxiliary" },
	"garage"            : { "fr" : "Garage", "en" : "Garage" },
	"garages"           : { "fr" : "Garages", "en" : "Garages" },
	"greenhouse"        : { "fr" : "Serre", "en" : "Greenhouse" },
	"hangar"            : { "fr" : "Hangar", "en" : "Hangar" },
	"hut"            	: { "fr" : "Cabane", "en" : "Hut" },
	"roof"            	: { "fr" : "Toit", "en" : "Roof" },
	"shed"            	: { "fr" : "Cabanon", "en" : "Shed" },
	"stable"            : { "fr" : "Étable", "en" : "Stable" },
	"sty"            	: { "fr" : "Sty", "en" : "Porcherie" },
	"transformer_tower" : { "fr" : "Tour à transformateur", "en" : "Transformer Tower" },
	"service"           : { "fr" : "Service", "en" : "Service" },
	"kiosk"            	: { "fr" : "Kiosque", "en" : "Kiosk" },
	"carport"           : { "fr" : "Carport", "en" : "Carport" },
	"ruins"            	: { "fr" : "Ruines", "en" : "Ruins" },
	"yes"            	: { "fr" : "Oui", "en" : "Yes" },
	"user defined"      : { "fr" : "Défini par l'utilisateur", "en" : "User Defined" }
}